<?xml version="1.0" encoding="UTF-8"?>
<Root>
  <PM_HEADER>
    <DONE_IRR>true</DONE_IRR>
  </PM_HEADER>
  <PARTIAL_MATRIX>
    <PARTIAL_DYN>
   0.000000000000000E+00   0.000000000000000E+00
   0.000000000000000E+00   0.000000000000000E+00
   0.000000000000000E+00   0.000000000000000E+00
   0.000000000000000E+00   0.000000000000000E+00
  -5.948421364367625E-02  -2.394741795877394E-02
   2.179419541649466E-02   9.455773820612754E-04
   0.000000000000000E+00   0.000000000000000E+00
   0.000000000000000E+00   0.000000000000000E+00
   0.000000000000000E+00   0.000000000000000E+00
   0.000000000000000E+00   0.000000000000000E+00
  -6.917711496792214E-02  -1.235477422357628E-02
  -4.494865221715870E-02   2.324141858106796E-03
   0.000000000000000E+00   0.000000000000000E+00
   0.000000000000000E+00   0.000000000000000E+00
   0.000000000000000E+00   0.000000000000000E+00
   0.000000000000000E+00   0.000000000000000E+00
   9.883560770998501E-01  -2.555638817172056E-01
   6.106090244021727E-01  -1.821156847920652E-01
   0.000000000000000E+00   0.000000000000000E+00
   0.000000000000000E+00   0.000000000000000E+00
   0.000000000000000E+00   0.000000000000000E+00
   0.000000000000000E+00   0.000000000000000E+00
  -7.088366605924629E-01   1.961819091313696E-01
   8.478213740301547E-01  -2.743256571489861E-01
   0.000000000000000E+00   0.000000000000000E+00
   0.000000000000000E+00   0.000000000000000E+00
   0.000000000000000E+00   0.000000000000000E+00
   0.000000000000000E+00   0.000000000000000E+00
  -2.318429762895770E+00  -1.090465075533171E-03
   4.224906987132461E-03  -1.190371774001460E-03
   0.000000000000000E+00   0.000000000000000E+00
   0.000000000000000E+00   0.000000000000000E+00
   0.000000000000000E+00   0.000000000000000E+00
   0.000000000000000E+00   0.000000000000000E+00
   4.109913800296924E-03   1.235662728145100E-03
  -2.409908729915752E+00   1.090353228913172E-03
    </PARTIAL_DYN>
  </PARTIAL_MATRIX>
</Root>
