<?xml version="1.0" encoding="UTF-8"?>
<Root>
  <IRREPS_INFO>
    <QPOINT_NUMBER>4</QPOINT_NUMBER>
    <QPOINT_GROUP_RANK>2</QPOINT_GROUP_RANK>
    <MINUS_Q_SYM>false</MINUS_Q_SYM>
    <NUMBER_IRR_REP>6</NUMBER_IRR_REP>
    <REPRESENTION.1>
      <NUMBER_OF_PERTURBATIONS>1</NUMBER_OF_PERTURBATIONS>
      <PERTURBATION.1>
        <DISPLACEMENT_PATTERN>
 -0.50561175909473310       -0.0000000000000000     
  0.69883520241602470        1.8516424990057938E-002
 -0.50561175909473299        7.3554395662076497E-019
  -0.0000000000000000        0.0000000000000000     
  -0.0000000000000000        0.0000000000000000     
  -0.0000000000000000        0.0000000000000000     
        </DISPLACEMENT_PATTERN>
      </PERTURBATION.1>
    </REPRESENTION.1>
    <REPRESENTION.2>
      <NUMBER_OF_PERTURBATIONS>1</NUMBER_OF_PERTURBATIONS>
      <PERTURBATION.1>
        <DISPLACEMENT_PATTERN>
  -0.0000000000000000       -0.0000000000000000     
  -0.0000000000000000       -0.0000000000000000     
  -0.0000000000000000       -0.0000000000000000     
 -0.31627772769448514       -0.0000000000000000     
 -0.26127360426808210      -0.85537880593430193     
 -0.31627772769448509       -5.4013089514689036E-017
        </DISPLACEMENT_PATTERN>
      </PERTURBATION.1>
    </REPRESENTION.2>
    <REPRESENTION.3>
      <NUMBER_OF_PERTURBATIONS>1</NUMBER_OF_PERTURBATIONS>
      <PERTURBATION.1>
        <DISPLACEMENT_PATTERN>
   0.0000000000000000       -0.0000000000000000     
   0.0000000000000000       -0.0000000000000000     
   0.0000000000000000       -0.0000000000000000     
 -0.63243054872801108       -0.0000000000000000     
  0.13066260323866152       0.42777387272491285     
 -0.63243054872801108       -1.1348221361414276E-016
        </DISPLACEMENT_PATTERN>
      </PERTURBATION.1>
    </REPRESENTION.3>
    <REPRESENTION.4>
      <NUMBER_OF_PERTURBATIONS>1</NUMBER_OF_PERTURBATIONS>
      <PERTURBATION.1>
        <DISPLACEMENT_PATTERN>
 -0.49432453819846861       -0.0000000000000000     
 -0.71479214302937599       -1.8939222085734338E-002
 -0.49432453819846928        2.8747273372242028E-018
  -0.0000000000000000       -0.0000000000000000     
  -0.0000000000000000       -0.0000000000000000     
  -0.0000000000000000       -0.0000000000000000     
        </DISPLACEMENT_PATTERN>
      </PERTURBATION.1>
    </REPRESENTION.4>
    <REPRESENTION.5>
      <NUMBER_OF_PERTURBATIONS>1</NUMBER_OF_PERTURBATIONS>
      <PERTURBATION.1>
        <DISPLACEMENT_PATTERN>
  -0.0000000000000000        0.0000000000000000     
  -0.0000000000000000        0.0000000000000000     
  -0.0000000000000000        0.0000000000000000     
 -0.70710678118654757       -0.0000000000000000     
   3.9612152234339120E-017   7.2437370773438421E-017
  0.70710678118654768        1.2565677236927159E-016
        </DISPLACEMENT_PATTERN>
      </PERTURBATION.1>
    </REPRESENTION.5>
    <REPRESENTION.6>
      <NUMBER_OF_PERTURBATIONS>1</NUMBER_OF_PERTURBATIONS>
      <PERTURBATION.1>
        <DISPLACEMENT_PATTERN>
 -0.70710678118654779       -0.0000000000000000     
  -3.4800516120691221E-016  -8.1251629265553118E-018
  0.70710678118654746       -2.5356112894431135E-018
   0.0000000000000000       -0.0000000000000000     
   0.0000000000000000       -0.0000000000000000     
   0.0000000000000000       -0.0000000000000000     
        </DISPLACEMENT_PATTERN>
      </PERTURBATION.1>
    </REPRESENTION.6>
  </IRREPS_INFO>
</Root>
